xrd_viewer/__init__.py
xrd_viewer/__main__.py
xrd_viewer/assets/logo.npy
xrd_viewer/assets/xrd.ui
xrd_viewer/xrd.py
xrd_viewer-1.0.0.dist-info/entry_points.txt
xrd_viewer-1.0.0.dist-info/LICENSE
xrd_viewer-1.0.0.dist-info/WHEEL
xrd_viewer-1.0.0.dist-info/METADATA
xrd_viewer-1.0.0.dist-info/RECORD
