Metadata-Version: 2.1
Name: xrd-viewer
Version: 1.0.0
Summary: Simple analysis tool for NeXus data files
Home-page: https://gitlab.com/merrx/xrd-viewer
Keywords: analysis,diffraction
Author: Sebastian Schenk
Author-email: sebastian.schenk@physik.uni-halle.de
Requires-Python: >=3.6,<4.0
Classifier: Programming Language :: Python :: 3
Classifier: Programming Language :: Python :: 3.6
Classifier: Programming Language :: Python :: 3.7
Requires-Dist: PyQt5 (>=5.0,<6.0)
Requires-Dist: h5py (>=2.9,<3.0)
Requires-Dist: matplotlib (>=3.0,<4.0)
Requires-Dist: numpy (>=1.15,<2.0)
